mypkgbraja/__init__.py
mypkgbraja-0.0.1.dist-info/METADATA
mypkgbraja-0.0.1.dist-info/WHEEL
mypkgbraja-0.0.1.dist-info/license.txt.txt
mypkgbraja-0.0.1.dist-info/top_level.txt
mypkgbraja-0.0.1.dist-info/RECORD
