Metadata-Version: 2.1
Name: mypkgbraja
Version: 0.0.1
Summary: adding number
Home-page: https://github.com/brajaprida/myrepository
Author: Braja Kishor Parida
Author-email: brajaprida@ymail.com
License: UNKNOWN
Platform: UNKNOWN
Classifier: Programming Language :: Python :: 3
Classifier: License :: OSI Approved :: MIT License
Classifier: Operating System :: OS Independent
